pyopencga/__init__.py
pyopencga/commons.py
pyopencga/exceptions.py
pyopencga/opencga_client.py
pyopencga/opencga_config.py
pyopencga/rest_response.py
pyopencga/retry.py
pyopencga/rest_clients/__init__.py
pyopencga/rest_clients/_parent_rest_clients.py
pyopencga/rest_clients/admin_client.py
pyopencga/rest_clients/alignment_client.py
pyopencga/rest_clients/clinical_analysis_client.py
pyopencga/rest_clients/cohort_client.py
pyopencga/rest_clients/disease_panel_client.py
pyopencga/rest_clients/family_client.py
pyopencga/rest_clients/file_client.py
pyopencga/rest_clients/ga4gh_client.py
pyopencga/rest_clients/individual_client.py
pyopencga/rest_clients/job_client.py
pyopencga/rest_clients/meta_client.py
pyopencga/rest_clients/organization_client.py
pyopencga/rest_clients/project_client.py
pyopencga/rest_clients/sample_client.py
pyopencga/rest_clients/study_client.py
pyopencga/rest_clients/user_client.py
pyopencga/rest_clients/variant_client.py
pyopencga/rest_clients/variant_operation_client.py
pyopencga/rest_clients/workflow_client.py
pyopencga_enterprise/__init__.py
pyopencga_enterprise/commons.py
pyopencga_enterprise/exceptions.py
pyopencga_enterprise/opencga_client.py
pyopencga_enterprise/opencga_config.py
pyopencga_enterprise/rest_response.py
pyopencga_enterprise/retry.py
pyopencga_enterprise/rest_clients/__init__.py
pyopencga_enterprise/rest_clients/_parent_rest_clients.py
pyopencga_enterprise/rest_clients/admin_client.py
pyopencga_enterprise/rest_clients/alignment_client.py
pyopencga_enterprise/rest_clients/clinical_analysis_client.py
pyopencga_enterprise/rest_clients/cohort_client.py
pyopencga_enterprise/rest_clients/cvdb_client.py
pyopencga_enterprise/rest_clients/disease_panel_client.py
pyopencga_enterprise/rest_clients/family_client.py
pyopencga_enterprise/rest_clients/federation_client.py
pyopencga_enterprise/rest_clients/file_client.py
pyopencga_enterprise/rest_clients/ga4gh_client.py
pyopencga_enterprise/rest_clients/individual_client.py
pyopencga_enterprise-3.1.0.dev30.dist-info/licenses/LICENSE
pyopencga_enterprise-3.1.0.dev30.dist-info/METADATA
pyopencga_enterprise-3.1.0.dev30.dist-info/WHEEL
pyopencga_enterprise-3.1.0.dev30.dist-info/top_level.txt
pyopencga_enterprise-3.1.0.dev30.dist-info/RECORD
