Metadata-Version: 2.4
Name: pyopencga_enterprise
Version: 3.1.0.dev30
Summary: A REST client for OpenCGA enterprise REST web services
Author: Daniel Perez-Gil
Author-email: daniel.perez@zettagenomics.com
License: Apache Software License
Project-URL: OpenCGA-enterprise, https://github.com/zetta-genomics/opencga-enterprise
Project-URL: Bug Reports, https://github.com/zetta-genomics/opencga-enterprise/issues
Keywords: zetta-genomics opencga-enterprise bioinformatics genomic database
Classifier: Development Status :: 5 - Production/Stable
Classifier: Intended Audience :: Developers
Classifier: Topic :: Scientific/Engineering :: Bio-Informatics
Classifier: License :: OSI Approved :: Apache Software License
Classifier: Programming Language :: Python :: 3
Classifier: Programming Language :: Python :: 3.5
License-File: LICENSE
Requires-Dist: requests>=2.7
Requires-Dist: pip>=7.1.2
Requires-Dist: pathlib>=1.0.1
Requires-Dist: pyyaml>=3.12
Requires-Dist: pandas>=1.1.5
Requires-Dist: flask>=2.0.3
Dynamic: author
Dynamic: author-email
Dynamic: classifier
Dynamic: description
Dynamic: description-content-type
Dynamic: keywords
Dynamic: license
Dynamic: license-file
Dynamic: project-url
Dynamic: requires-dist
Dynamic: summary
